unit_converter_plus/__init__.py
unit_converter_plus/cli.py
unit_converter_plus/converter.py
unit_converter_plus/units/__init__.py
unit_converter_plus/units/angle.py
unit_converter_plus/units/area.py
unit_converter_plus/units/conductivity.py
unit_converter_plus/units/data.py
unit_converter_plus/units/earthquake.py
unit_converter_plus/units/energy.py
unit_converter_plus/units/force.py
unit_converter_plus/units/frequency.py
unit_converter_plus/units/length.py
unit_converter_plus/units/luminosity.py
unit_converter_plus/units/mass.py
unit_converter_plus/units/power.py
unit_converter_plus/units/pressure.py
unit_converter_plus/units/speed.py
unit_converter_plus/units/temperature.py
unit_converter_plus/units/Time.py
unit_converter_plus/units/volume.py
unit_converter_plus-0.1.1.dist-info/entry_points.txt
unit_converter_plus-0.1.1.dist-info/LICENSE
unit_converter_plus-0.1.1.dist-info/METADATA
unit_converter_plus-0.1.1.dist-info/WHEEL
unit_converter_plus-0.1.1.dist-info/RECORD
